[
  {
    "original_message": "โก๏ธะกะฃะะฌะคะะข ะะะะะฎ - ะะณะธะฟะตั ๐ช๐ฌ\n\n๐ะะพัั - ะงะพัะฝะพะผะพัััะบ\n๐ะฆัะฝะฐ - 42 500 ะณัะฝ/ั (ะผะพะถะปะธะฒะฐ ะดะพััะฐะฒะบะฐ)\n\n๐ฑะขะตะปะตัะพะฝัะนัะต:\n\n+38(063)-639-02-61\n+38(050)-301-79-08\n\n๐ย ะะฐั ัะฐะนั\n\nโ๏ธย ะะธ ั ะขะตะปะตะณัะฐะผ",
    "extracted_info": {
      "country": "Ukraine",
      "region": null,
      "category": null,
      "amount": null,
      "price": "500.0",
      "currency": "UAH",
      "description": null,
      "phone": null
    }
  },
  {
    "original_message": "ะัะพะดะฐััััั  ะบัะบัััะดะทัะฝั ะฒัะดัะพะดะธ 1 ะบะฐัะตะณะพััั ( 75%ะทะตัะฝะพะฒะฐ)\nะะฑ'ัะผ +-50 ัะพะฝ.\nะะพะทัะฐััะฝะพะบ ะณะพััะฒะบะฐ ะฐะฑะพ ะฝะฐ ัะฐััะฝะพะบ ะคะะ ะฑะตะท ะะะ.\nะััะพะฒะพะณัะฐะดััะบะฐ ะพะฑะป.\nะขะตะป.: 068-305-85-20\nะะฐัะฐะปัั",
    "extracted_info": {
      "country": "Ukraine",
      "region": null,
      "category": "Corn",
      "amount": "50.0",
      "price": null,
      "currency": "UAH",
      "description": null,
      "phone": null
    }
  },
  {
    "original_message": "๐ฅะะฐะบัะฟะฐะตะผ ะทะตัะฝะพะฒัะต ะธ ะผะฐัะปะธัะฝัะต ะฟะพ ะฒัะณะพะดะฝัะผ ัะตะฝะฐะผโ๏ธ\n\nโ๏ธ ะะฐะบัะฟะฐะตะผ ั ะผะตััะฐ๐๐\n\n๐ ะะดะตััะฐ\n๐พะัะตะฝะธัะฐ - 8300/8300/7900 ะณัะฝ \n๐ปะัะบัััะทะฐ - 212๐ต\n๐พะะพัะพั ะถะตะปััะน - 245๐ต\n๐ฑะกะพั - 330๐ต\n๐ผะะฐะฟั ะะะ/ะฝะต ะะะ - 455๐ต\n๐ปะะพะดัะพะปะฝัั - 535๐ต (ะะฐัะปะพ 46+)\n๐ฟะัะฝ ะบะพัะธัะฝะตะฒัะน - 565๐ต\n\n๐ ะะทะผะฐะธะป\n๐พะัะตะฝะธัะฐ - 197/195/184๐ต\n๐พะฏัะผะตะฝั - 184๐ต\n๐พะะพัะพั - 245๐ต\n๐ปะะพะดัะพะปะฝัั - 22000 ะณัะฝ\n\n๐ ะะฐั ะะธะฝะฝะธัะบะฐั ะพะฑะป.\n๐ป ะะพะดัะพะปะฝัั - 20800ะณัะฝ (ะฑะตะท ะผะฐัะปะฐ)\n๐ป ะะพะดัะพะปะฝัั - 21250ะณัะฝ ะผะฐัะปะพ 46%\n๐ฝ ะัะบัััะทะฐ - 7200ะณัะฝ\n\nโ๏ธะะตัะฟะปะฐัะฝะพะต ััะฐะฝะตะฝะธะต ะฟะพะดัะพะปะฝะตัะฝะธะบะฐโ๏ธ\n\n๐ ะะตะฝะฐ ะงะตัะฝะธะณะพะฒัะบะฐั ะพะฑะป.\n๐พ ะัะตะฝะธัะฐ - 8000/8000/7800ะณัะฝ\n๐ป ะัะบัััะทะฐ - 205๐ต\n๐พ ะะพัะพั - 240๐ต\n๐ป ะะพะดัะพะปะฝัั - 21200ะณัะฝ\n\n\nโ๏ธ ะัััะธะต ัะตะฝั\nโ๏ธ ะัััััะน ัะฐัััั\nโ๏ธ ะัะพะทัะฐัะฝัะต ััะปะพะฒะธั\n\n๐ะะพะฝัะฐะบั ะดะปั ัะฒัะทะธ:\n+380932182822 ะกะตัะณะตะน ๐พ",
    "extracted_info": {
      "country": "Ukraine",
      "region": "ะะดะตััะบะฐ ะพะฑะป.",
      "category": "Wheat",
      "amount": null,
      "price": "7900.0",
      "currency": "UAH",
      "description": null,
      "phone": "+380932182822"
    }
  },
  {
    "original_message": "๐ข ะกะฃะะฌะคะะข ะะะฎะะะะะฎ - ะขััะตััะธะฝะฐ ๐น๐ท\n\n๐นะกะบะปะฐะด - ะะธัะฒ\n๐นะฆัะฝะฐ - 17 500 ะณัะฝ/ั (ะฒัะด 5 ัะพะฝะฝ)\n๐นะขะพะฒะฐั ัะตััะธััะบะพะฒะฐะฝะพ ะฒ ะฃะบัะฐัะฝั\n\n\n๐ฑะขะตะปะตัะพะฝัะนัะต:\n\n+38(063)-639-02-61\n+38(050)-301-79-08\n\n๐ย ะะฐั ัะฐะนั\n\n๐  ะะธ ั ะขะตะปะตะณัะฐะผ",
    "extracted_info": {
      "country": "Ukraine",
      "region": "ะะธัะฒััะบะฐ ะพะฑะป.",
      "category": null,
      "amount": "5.0",
      "price": "500.0",
      "currency": "UAH",
      "description": null,
      "phone": null
    }
  },
  {
    "original_message": "ะัะฟะปั ะฝะฐ ะฟะพััะพัะฝะฝะพะน ะพัะฝะพะฒะต  ะพั ะฟัะพะธะทะฒะพะดะธัะตะปั:\n- ะปัะฝ ะบะพัะธัะฝะตะฒัะน - 580โฌ+\n- ะปัะฝ ะทะพะปะพัะธัััะน - 650โฌ+\n- ะฟัะพัะพ ะถัะปัะพะต;\n- ัะตัะตะฒะธัะฐ ะบัะฐัะฝะฐั;\n+37377743051(Viber / WhatsApp / Telegram)ะกะตัะณะตะน",
    "extracted_info": {
      "country": "Ukraine",
      "region": null,
      "category": null,
      "amount": null,
      "price": null,
      "currency": "UAH",
      "description": null,
      "phone": "+37377743051"
    }
  }
]